MANIFEST.in
README.md
setup.py
pypispy_pypi_test/__init__.py
pypispy_pypi_test/__init__.pyc
pypispy_pypi_test.egg-info/PKG-INFO
pypispy_pypi_test.egg-info/SOURCES.txt
pypispy_pypi_test.egg-info/dependency_links.txt
pypispy_pypi_test.egg-info/top_level.txt