Metadata-Version: 1.0
Name: pypispy-pypi-test
Version: 0.1
Summary: pypispy-pypi-test
